milvus_cloud/__init__.py
milvus_cloud/settings.py
milvus_cloud/client/__init__.py
milvus_cloud/client/abstract.py
milvus_cloud/client/asynch.py
milvus_cloud/client/check.py
milvus_cloud/client/client_hooks.py
milvus_cloud/client/exceptions.py
milvus_cloud/client/grpc_handler.py
milvus_cloud/client/http_handler.py
milvus_cloud/client/pool.py
milvus_cloud/client/prepare.py
milvus_cloud/client/stub.py
milvus_cloud/client/types.py
milvus_cloud/client/utils.py
milvus_cloud/client/hooks/__init__.py
milvus_cloud/client/hooks/abstract.py
milvus_cloud/grpc_gen/__init__.py
milvus_cloud/grpc_gen/milvus_pb2.py
milvus_cloud/grpc_gen/milvus_pb2_grpc.py
milvus_cloud/grpc_gen/status_pb2.py
milvus_cloud/grpc_gen/status_pb2_grpc.py
pymilvus_cloud-0.0.3.dist-info/LICENSE
pymilvus_cloud-0.0.3.dist-info/METADATA
pymilvus_cloud-0.0.3.dist-info/WHEEL
pymilvus_cloud-0.0.3.dist-info/top_level.txt
pymilvus_cloud-0.0.3.dist-info/RECORD
